repeaterbook/__init__.py
repeaterbook/database.py
repeaterbook/models.py
repeaterbook/py.typed
repeaterbook/queries.py
repeaterbook/services.py
repeaterbook/utils.py
repeaterbook-0.2.2.dist-info/METADATA
repeaterbook-0.2.2.dist-info/WHEEL
repeaterbook-0.2.2.dist-info/licenses/LICENSE
repeaterbook-0.2.2.dist-info/RECORD
