Metadata-Version: 2.4
Name: repeaterbook
Version: 0.2.2
Summary: Python utility to work with data from RepeaterBook.
Project-URL: homepage, https://github.com/MicaelJarniac/repeaterbook
Project-URL: source, https://github.com/MicaelJarniac/repeaterbook
Project-URL: download, https://pypi.org/project/repeaterbook/#files
Project-URL: changelog, https://github.com/MicaelJarniac/repeaterbook/blob/main/docs/CHANGELOG.md
Project-URL: documentation, https://repeaterbook.readthedocs.io
Project-URL: issues, https://github.com/MicaelJarniac/repeaterbook/issues
Author-email: Micael Jarniac <micael@jarniac.dev>
License: MIT
License-File: LICENSE
Classifier: Development Status :: 1 - Planning
Classifier: License :: OSI Approved :: MIT License
Classifier: Natural Language :: English
Classifier: Operating System :: OS Independent
Classifier: Programming Language :: Python :: 3
Classifier: Typing :: Typed
Requires-Python: >=3.10
Requires-Dist: aiohttp>=3.11.14
Requires-Dist: anyio>=4.9.0
Requires-Dist: attrs>=25.3.0
Requires-Dist: haversine>=2.9.0
Requires-Dist: loguru>=0.7.3
Requires-Dist: pycountry>=24.6.1
Requires-Dist: sqlmodel>=0.0.24
Requires-Dist: tqdm>=4.67.1
Requires-Dist: yarl>=1.18.3
